tftb/__init__.py
tftb/utils.py
tftb/generators/__init__.py
tftb/generators/amplitude_modulated.py
tftb/generators/analytic_signals.py
tftb/generators/frequency_modulated.py
tftb/generators/misc.py
tftb/generators/noise.py
tftb/generators/utils.py
tftb/generators/tests/__init__.py
tftb/generators/tests/test_amplitude_modulations.py
tftb/generators/tests/test_analytic_signals.py
tftb/generators/tests/test_frequency_modulations.py
tftb/generators/tests/test_misc.py
tftb/generators/tests/test_noise.py
tftb/generators/tests/test_utils.py
tftb/processing/__init__.py
tftb/processing/affine.py
tftb/processing/ambiguity.py
tftb/processing/base.py
tftb/processing/cohen.py
tftb/processing/freq_domain.py
tftb/processing/linear.py
tftb/processing/plotifl.py
tftb/processing/postprocessing.py
tftb/processing/reassigned.py
tftb/processing/time_domain.py
tftb/processing/utils.py
tftb/processing/tests/__init__.py
tftb/processing/tests/test_ambiguity.py
tftb/processing/tests/test_cohen.py
tftb/processing/tests/test_freq_domain.py
tftb/processing/tests/test_linear.py
tftb/processing/tests/test_postprocessing.py
tftb/processing/tests/test_time_domain.py
tftb/processing/tests/test_utils.py
tftb/tests/__init__.py
tftb/tests/test_base.py
tftb/tests/test_utils.py
tftb-0.1.1.dist-info/METADATA
tftb-0.1.1.dist-info/WHEEL
tftb-0.1.1.dist-info/top_level.txt
tftb-0.1.1.dist-info/RECORD
