Metadata-Version: 2.1
Name: tftb
Version: 0.1.1
Summary: Python module for time-frequency analysis.
Home-page: https://github.com/scikit-signal/tftb
Maintainer: Jaidev Deshpande
Maintainer-email: deshpande.jaidev@gmail.com
License: new BSD
Download-URL: https://pypi.org/project/tftb/#files
Platform: UNKNOWN
Requires-Dist: numpy
Requires-Dist: scipy
Requires-Dist: matplotlib
